CHANGES.rst
MANIFEST.in
README.rst
setup.py
mdx_sections/__init__.py
mdx_sections.egg-info/PKG-INFO
mdx_sections.egg-info/SOURCES.txt
mdx_sections.egg-info/dependency_links.txt
mdx_sections.egg-info/not-zip-safe
mdx_sections.egg-info/top_level.txt