Metadata-Version: 1.0
Name: mdx-sections
Version: 0.1
Summary: Python-Markdown extension to add a small amount of structure to Markdown documents.
Home-page: http://github.com/jessedhillon/mdx_sections
Author: Jesse Dhillon
Author-email: jesse@dhillon.com
License: UNKNOWN
Keywords: web wsgi bfg pylons pyramid
Platform: UNKNOWN
Classifier: Programming Language :: Python
